{"cameraMode":{"drawMode":0,"name":"Shaded","section":"Shading Mode"},"sceneLighting":false,"audioPlay":false,"sceneViewState":{"m_AlwaysRefresh":false,"showFog":true,"showSkybox":false,"showFlares":true,"showImageEffects":true,"showParticleSystems":true,"showVisualEffectGraphs":true,"m_FxEnabled":true},"in2DMode":false,"pivot":{"x":1.0964940786361695,"y":2.3671257495880129,"z":-1.394070029258728},"rotation":{"x":-0.000985060236416757,"y":0.668746829032898,"z":0.0013617192162200809,"w":-0.7454385757446289},"size":3.328568458557129,"orthographic":false}